{
  "FC ARENA": ["N. Quang Hải", "V. Văn Thanh", "Đ. Văn Hậu"],
  "Viettel FC": ["N. Hoàng Đức", "Bùi Tiến Dũng", "P. Tuấn Hải"],
  "Hải Phòng FC": ["Lương Xuân Trường", "Mpande", "Lucao"],
  "Hong Linh Ha Tinh": ["Trần Phi Sơn", "Diallo", "Vũ Quang Nam"],
  "MerryLand Quy Nhon": ["Alan Grafite", "Leo Artur", "Đặng Văn Lâm"],
  "Dong A Thanh Hoa": ["Rimario Gordon", "Luis Antonio", "Trịnh Văn Lợi"],
  "Mansfield Town": ["Lucas Akins", "Davis Keillor-Dunn", "Will Swan"],
  "Chesterfield": ["Will Grigg", "Joe Quigley", "Tom Naylor"]
}
